{
  "input": {
    "input1": "Sheet1!B2",
    "input2": "Sheet1!B3",
    "input3": "Sheet1!B4"
  },
  "output": [
    {"cell":"Sheet1!B2"},
    {"cell":"Sheet1!B5"},
    {"cell":"Sheet1!B6"},
    {"cell":"Sheet1!B7"},
    {"cell":"Sheet1!B8"},
    {"cell":"Sheet1!B9"},
    {"cell":"Sheet1!G5"},
    {"cell":"Sheet1!G6"},
    {"cell":"Sheet1!G8"},
    {"cell":"Sheet1!G9"},
    {"cell":"Sheet1!G10"},
    {"cell":"Sheet1!B14"},
    {"cell":"Sheet1!B15"},
    {"cell":"Sheet1!B16"},
    {"cell":"Sheet1!B17"},
    {"cell":"Sheet1!B18"}
  ]
}
